{
    "name": "GAUSSIAN_MODEL_2",
    "coeff": [
        0.9998456704266544,
        9.21631739596086e-09,
        -0.00032635637976211496,
        6.853191888361663e-08,
        0.9308139627304847,
        4.389461941384111e-06
    ],
    "lsf_data": [
        {
            "file_arc": "../exposures/ARC-Xe_CLEAR_20MAS_H_PRM.fits",
            "file_listLines": "../text/Xe.txt",
            "file_wavecal": "../exposures/WAVECAL_TABLE_20MAS_H.fits",
            "file_slitlet": "../exposures/SLITLET_TABLE_20MAS_H.fits",
            "slice": 0,
            "detID": 1,
            "normal": "Normal",
            "file_flat": null
        }
    ]
}